CONTRIBUTING.md
askanna/__init__.py
askanna/init.py
askanna/settings.py
askanna/cli/__init__.py
askanna/cli/__main__.py
askanna/cli/artifact.py
askanna/cli/create.py
askanna/cli/init.py
askanna/cli/job.py
askanna/cli/login.py
askanna/cli/logout.py
askanna/cli/project.py
askanna/cli/push.py
askanna/cli/result.py
askanna/cli/run.py
askanna/cli/utils.py
askanna/cli/variable.py
askanna/cli/workspace.py
askanna/cli/run_utils/__init__.py
askanna/cli/run_utils/__main__.py
askanna/cli/run_utils/get_package.py
askanna/cli/run_utils/get_payload.py
askanna/cli/run_utils/get_run_manifest.py
askanna/cli/run_utils/push_artifact.py
askanna/cli/run_utils/push_metrics.py
askanna/cli/run_utils/push_result.py
askanna/cli/run_utils/push_variables.py
askanna/cli/run_utils/utils.py
askanna/config/__init__.py
askanna/config/api_url.py
askanna/config/project.py
askanna/config/server.py
askanna/config/utils.py
askanna/core/__init__.py
askanna/core/collector.py
askanna/core/download.py
askanna/core/exceptions.py
askanna/core/push.py
askanna/core/upload.py
askanna/core/dataclasses/__init__.py
askanna/core/dataclasses/base.py
askanna/core/dataclasses/job.py
askanna/core/dataclasses/package.py
askanna/core/dataclasses/project.py
askanna/core/dataclasses/relation.py
askanna/core/dataclasses/run.py
askanna/core/dataclasses/variable.py
askanna/core/dataclasses/workspace.py
askanna/core/utils/__init__.py
askanna/core/utils/at_exit.py
askanna/core/utils/file.py
askanna/core/utils/main.py
askanna/core/utils/object.py
askanna/core/utils/settings.py
askanna/core/utils/suuid.py
askanna/core/utils/validate.py
askanna/gateways/__init__.py
askanna/gateways/api_client.py
askanna/gateways/auth.py
askanna/gateways/job.py
askanna/gateways/package.py
askanna/gateways/project.py
askanna/gateways/run.py
askanna/gateways/utils.py
askanna/gateways/variable.py
askanna/gateways/workspace.py
askanna/sdk/__init__.py
askanna/sdk/job.py
askanna/sdk/mixins.py
askanna/sdk/package.py
askanna/sdk/project.py
askanna-0.24.0.dist-info/METADATA
askanna-0.24.0.dist-info/WHEEL
askanna-0.24.0.dist-info/entry_points.txt
askanna-0.24.0.dist-info/licenses/AUTHORS.md
askanna-0.24.0.dist-info/licenses/LICENSE
askanna-0.24.0.dist-info/RECORD
