Metadata-Version: 2.1
Name: askanna
Version: 0.24.0
Summary: The AskAnna CLI & Python SDK is part of the AskAnna platform to kickstart your data science projects
Project-URL: Homepage, https://askanna.io
Project-URL: Documentation Python SDK, https://docs.askanna.io/python-sdk/
Project-URL: Documentation CLI, https://docs.askanna.io/cli/
Project-URL: Documentation AskAnna, https://docs.askanna.io/
Project-URL: Changelog, https://gitlab.com/askanna/askanna-python/-/blob/master/CHANGELOG.md
Project-URL: Issue Tracker, https://gitlab.com/askanna/askanna-python/issues
Project-URL: Source, https://gitlab.com/askanna/askanna-python
Author-email: AskAnna Team <support@askanna.io>
Maintainer-email: AskAnna Team <support@askanna.io>
License-Expression: BSD-3-Clause
License-File: AUTHORS.md
License-File: LICENSE
Keywords: ai,askanna,data,datascience,ml,versioncontrol
Classifier: Development Status :: 4 - Beta
Classifier: Intended Audience :: Developers
Classifier: Intended Audience :: Education
Classifier: Intended Audience :: Information Technology
Classifier: Intended Audience :: Science/Research
Classifier: License :: OSI Approved :: BSD License
Classifier: Natural Language :: English
Classifier: Programming Language :: Python :: 3
Classifier: Programming Language :: Python :: 3.8
Classifier: Programming Language :: Python :: 3.9
Classifier: Programming Language :: Python :: 3.10
Classifier: Programming Language :: Python :: 3.11
Classifier: Programming Language :: Python :: 3.12
Classifier: Topic :: Scientific/Engineering
Classifier: Topic :: Scientific/Engineering :: Artificial Intelligence
Classifier: Topic :: Scientific/Engineering :: Information Analysis
Requires-Python: >=3.8
Requires-Dist: backports-zoneinfo>=0.2.1; python_version < '3.9'
Requires-Dist: click<9.0.0,>=7.1.2
Requires-Dist: cookiecutter<3.0.0,>1.7.0
Requires-Dist: croniter<3.0.0,>=1.0.15
Requires-Dist: email-validator<3.0.0
Requires-Dist: futures~=2.2.0; python_version < '3.10'
Requires-Dist: gitpython<4.0.0,>=3.1.0
Requires-Dist: igittigitt<3.0.0,>=2.0.2
Requires-Dist: python-dateutil<3.0.0,>=2.8.0
Requires-Dist: python-slugify<9.0.0,>=7.0.0
Requires-Dist: pyyaml<7.0.0,>=5.3.1
Requires-Dist: requests<3.0.0,>=2.22.0
Requires-Dist: resumable~=0.1.1
Requires-Dist: tzlocal<6.0,>=2.1
Provides-Extra: dev
Requires-Dist: askanna[test]; extra == 'dev'
Requires-Dist: bandit~=1.7.7; extra == 'dev'
Requires-Dist: black~=24.2.0; extra == 'dev'
Requires-Dist: hatch~=1.9.3; extra == 'dev'
Requires-Dist: isort~=5.13.2; extra == 'dev'
Requires-Dist: pre-commit~=3.6.2; extra == 'dev'
Requires-Dist: python-dotenv~=1.0.1; extra == 'dev'
Provides-Extra: test
Requires-Dist: faker~=23.2.1; extra == 'test'
Requires-Dist: numpy>=1.24.4; extra == 'test'
Requires-Dist: pytest-cov~=4.1.0; extra == 'test'
Requires-Dist: pytest~=8.0.1; extra == 'test'
Requires-Dist: responses~=0.25.0; extra == 'test'
Requires-Dist: ruff~=0.2.2; extra == 'test'
Requires-Dist: urllib3~=1.26.18; extra == 'test'
